tf_adan/__init__.py
tf_adan/adan.py
tf_adan/test_adan_dense.py
tf_adan/test_adan_sparse.py
tf_adan/torch_adan.py
tf_adan/utils.py
adan_tensorflow-1.0.1.dist-info/METADATA
adan_tensorflow-1.0.1.dist-info/WHEEL
adan_tensorflow-1.0.1.dist-info/top_level.txt
adan_tensorflow-1.0.1.dist-info/RECORD
